setup.cfg
setup.py
jn_import/__init__.py
jn_import/jn_import.py
jn_import.egg-info/PKG-INFO
jn_import.egg-info/SOURCES.txt
jn_import.egg-info/dependency_links.txt
jn_import.egg-info/not-zip-safe
jn_import.egg-info/top_level.txt