Metadata-Version: 1.1
Name: jn-import
Version: 0.4
Summary: Jupyter Notebooks Importing Tools
Home-page: https://github.com/maoxin/jn_import
Author: maoxin
Author-email: maoxin.horizon@gmail.com
License: MIT
Download-URL: https://github.com/maoxin/jn_import/tarball/0.4
Platform: UNKNOWN
